odoo/addons/auth_oauth_environment/README.rst
odoo/addons/auth_oauth_environment/__init__.py
odoo/addons/auth_oauth_environment/__manifest__.py
odoo/addons/auth_oauth_environment/models/__init__.py
odoo/addons/auth_oauth_environment/models/auth_oauth_provider.py
odoo/addons/auth_oauth_environment/models/res_config_settings.py
odoo/addons/auth_oauth_environment/static/description/icon.png
odoo/addons/auth_oauth_environment/views/auth_oauth_provider.xml
odoo11_addon_auth_oauth_environment-11.0.1.0.0.99.dev3.dist-info/METADATA
odoo11_addon_auth_oauth_environment-11.0.1.0.0.99.dev3.dist-info/WHEEL
odoo11_addon_auth_oauth_environment-11.0.1.0.0.99.dev3.dist-info/top_level.txt
odoo11_addon_auth_oauth_environment-11.0.1.0.0.99.dev3.dist-info/RECORD
